LICENSE
README.md
setup.py
pycaptcha_guard/__init__.py
pycaptcha_guard/base_page.py
pycaptcha_guard/captcha.py
pycaptcha_guard.egg-info/PKG-INFO
pycaptcha_guard.egg-info/SOURCES.txt
pycaptcha_guard.egg-info/dependency_links.txt
pycaptcha_guard.egg-info/requires.txt
pycaptcha_guard.egg-info/top_level.txt
pycaptcha_guard/capsolver_solution/__init__.py
pycaptcha_guard/capsolver_solution/google_recaptcha.py
pycaptcha_guard/capsolver_solution/textcaptcha.py
pycaptcha_guard/captcha_locators/__init__.py
pycaptcha_guard/captcha_locators/google_recaptcha_locator.py
pycaptcha_guard/captcha_locators/textcaptcha_locator.py
pycaptcha_guard/common_components/__init__.py
pycaptcha_guard/common_components/constants.py
pycaptcha_guard/nopecha_solution/__init__.py
pycaptcha_guard/nopecha_solution/google_recaptcha.py
pycaptcha_guard/nopecha_solution/textcaptcha.py