Metadata-Version: 2.1
Name: pycaptcha-guard
Version: 0.3.6
Summary: Solve any kind of captcha like human
Author: AleenaMuskan
Author-email: aleenakhanraees40@gmail.com
License: MIT
Requires-Python: >=3.9
License-File: LICENSE
Requires-Dist: nopecha>=1.0.8
Requires-Dist: selenium>=4.16.0
Requires-Dist: pillow==10.1.0
Requires-Dist: pyautogui==0.9.54
Requires-Dist: capsolver>=1.0.7
